rbkcli/__init__.py
rbkcli/base/__init__.py
rbkcli/base/api.py
rbkcli/base/essentials.py
rbkcli/base/jsops.py
rbkcli/base/tools.py
rbkcli/core/__init__.py
rbkcli/core/target.py
rbkcli/core/handlers/__init__.py
rbkcli/core/handlers/callback.py
rbkcli/core/handlers/cmdlets.py
rbkcli/core/handlers/customizer.py
rbkcli/core/handlers/environment.py
rbkcli/core/handlers/inputs.py
rbkcli/core/handlers/jsometa.py
rbkcli/core/handlers/meta.py
rbkcli/core/handlers/operations.py
rbkcli/core/handlers/outputs.py
rbkcli/interface/__init__.py
rbkcli/interface/cli.py
rbkcli/interface/rbk_cli.py
rbkcli-1.0.0b2.dist-info/LICENSE
rbkcli-1.0.0b2.dist-info/METADATA
rbkcli-1.0.0b2.dist-info/WHEEL
rbkcli-1.0.0b2.dist-info/entry_points.txt
rbkcli-1.0.0b2.dist-info/top_level.txt
rbkcli-1.0.0b2.dist-info/RECORD
