Metadata-Version: 2.1
Name: rbkcli
Version: 1.0.0b2
Summary: A python package that creates a CLI conversion from Rubrik APIs
Home-page: https://github.com/rubrikinc/rbkcli
Author: Bruno Manesco
Author-email: bruno.manesco@rubrik.com
License: UNKNOWN
Platform: UNKNOWN
Classifier: Programming Language :: Python :: 3
Classifier: License :: OSI Approved :: MIT License
Classifier: Operating System :: OS Independent
Requires-Dist: requests
Requires-Dist: Paramiko
Requires-Dist: argcomplete
Requires-Dist: PyYAML
Requires-Dist: urllib3
